skuvault/__init__.py
skuvault/api.py
skuvault-1.1.2.dist-info/LICENSE
skuvault-1.1.2.dist-info/METADATA
skuvault-1.1.2.dist-info/WHEEL
skuvault-1.1.2.dist-info/top_level.txt
skuvault-1.1.2.dist-info/RECORD
