Metadata-Version: 2.1
Name: skuvault
Version: 1.1.2
Summary: A Python library for the SkuVault API
Home-page: https://github.com/Penlo/skuvault-python
Author: Nathan Head
Author-email: headn90@gmail.com
License: MIT
Project-URL: Bug Tracker, https://github.com/Penlo/skuvault-python/issues
Platform: UNKNOWN
Classifier: Programming Language :: Python :: 3
Classifier: License :: OSI Approved :: MIT License
Classifier: Operating System :: OS Independent
License-File: LICENSE
